{
  "parent": "minecraft:recipes/root",
  "rewards": {
    "recipes": [
      "rgbblocks:concrete_powder_coloring"
    ]
  },
  "criteria": {
    "has_paint_bucket_and_concrete_powder": {
      "trigger": "minecraft:inventory_changed",
      "conditions": {
        "items": [
          {
            "items": [
              "rgbblocks:paint_bucket"
            ]
          },
          {
            "items": [
              "rgbblocks:concrete_powder"
            ]
          }
        ]
      }
    },
    "has_the_recipe": {
      "trigger": "minecraft:recipe_unlocked",
      "conditions": {
        "recipe": "rgbblocks:concrete_powder_coloring"
      }
    }
  },
  "requirements": [
    [
      "has_paint_bucket_and_concrete_powder",
      "has_the_recipe"
    ]
  ]
}